{
    "experiment_name": "fine-tuning 4layer",
    "gametype": "strat",
    "fine_tune": "recent",
    "n_epochs": 500,
    "lr": 1e-05,
    "weight_decay": 0.0001,
    "batch_size": 4096,
    "train_test_split": 0.8,
    "n_layers": 8,
    "n_heads": 8,
    "d_model": 128,
    "d_head": 16,
    "d_mlp": 512,
    "act_fn": "relu",
    "normalization_type": null,
    "device": "cuda",
    "seed": 1337,
    "save_losses": false,
    "save_checkpoints": false,
    "eval_model": false,
    "d_vocab": 11,
    "d_vocab_out": 10,
    "n_ctx": 10,
    "init_weights": true
}